flarestack/__init__.py
flarestack/analyses/__init__.py
flarestack/analyses/agn_cores/README.md
flarestack/analyses/agn_cores/__init__.py
flarestack/analyses/agn_cores/catalogues/lowluminosity_irselected_north.npy
flarestack/analyses/agn_cores/catalogues/radioloud_irselected.npy
flarestack/analyses/agn_cores/catalogues/radioloud_irselected_north.npy
flarestack/analyses/agn_cores/catalogues/radioloud_radioselected.npy
flarestack/analyses/agn_cores/catalogues/radioloud_radioselected_north.npy
flarestack/analyses/agn_cores/catalogues/raw/LLAGN_2rxs2AllWiseSayfertness_no3LACbl_April2020_small.fits
flarestack/analyses/agn_cores/catalogues/raw/RadioLoudAGN_IRSelected_2rxsXmmsl2AllWise_no3LACbl_June2019_small.fits
flarestack/analyses/agn_cores/catalogues/raw/RadioLoudAGN_RadioSelected_2rxsXmmsl2NvssAllWise_no3LACbl.fits
flarestack/analyses/agn_cores/create_catalogue.py
flarestack/analyses/agn_cores/diffuse_dataset/__init__.py
flarestack/analyses/agn_cores/diffuse_dataset/radioloud_radio/__init__.py
flarestack/analyses/agn_cores/diffuse_dataset/test_completeness_diffuse_8years_cluster_collectdata.py
flarestack/analyses/agn_cores/loop_over_catalogues.py
flarestack/analyses/agn_cores/scripts_for_unblinding/__init__.py
flarestack/analyses/agn_cores/scripts_for_unblinding/agn_catalogues/__init__.py
flarestack/analyses/agn_cores/scripts_for_unblinding/agn_catalogues/create_ir_selected_agn_north_catalogue.py
flarestack/analyses/agn_cores/scripts_for_unblinding/agn_catalogues/create_llagn_north_catalogue.py
flarestack/analyses/agn_cores/scripts_for_unblinding/agn_catalogues/create_radio_selected_agn_north_catalogue.py
flarestack/analyses/agn_cores/scripts_for_unblinding/create_agn_samples/__init__.py
flarestack/analyses/agn_cores/scripts_for_unblinding/create_agn_samples/create_ir_selected_agn_north_catalogue.py
flarestack/analyses/agn_cores/scripts_for_unblinding/create_agn_samples/create_llagn_north_catalogue.py
flarestack-2.4.9.dist-info/LICENSE.txt
flarestack-2.4.9.dist-info/METADATA
flarestack-2.4.9.dist-info/WHEEL
flarestack-2.4.9.dist-info/RECORD
