Metadata-Version: 2.3
Name: flarestack
Version: 2.4.9
Summary: Package for unbinned likelihood analysis of physics data
License: MIT
Keywords: astroparticle physics,science,unbinned likelihood,IceCube
Author: Robert Stein
Author-email: rdstein@caltech.edu
Maintainer: Robert Stein
Maintainer-email: rdstein@caltech.edu
Requires-Python: >=3.9,<4.0
Classifier: License :: OSI Approved :: MIT License
Classifier: Operating System :: OS Independent
Classifier: Programming Language :: Python :: 3
Classifier: Programming Language :: Python :: 3.9
Classifier: Programming Language :: Python :: 3.10
Classifier: Programming Language :: Python :: 3.11
Classifier: Programming Language :: Python :: 3.12
Classifier: Programming Language :: Python :: 3.13
Requires-Dist: astropy (>=5.1,<7.0)
Requires-Dist: coveralls (>=3.3.1,<5.0.0)
Requires-Dist: healpy (>=1.16.1,<2.0.0)
Requires-Dist: jupyter (>=1.0.0,<2.0.0)
Requires-Dist: matplotlib (>=3.5.2,<4.0.0)
Requires-Dist: numexpr (>=2.8.3,<3.0.0)
Requires-Dist: numpy (>=1.23.1,<2.0.0)
Requires-Dist: scipy (>=1.13.1,<2.0.0)
Requires-Dist: urllib3 (==2.3.0)
Project-URL: Documentation, https://flarestack.readthedocs.io/en/latest/?badge=latest
Project-URL: Repository, https://github.com/icecube/flarestack
